{
  "schema_version": 1,
  "phase_id": "P18",
  "phase_name": "Spec Kit Bridge",
  "original_path": "design/phases/P18-spec-kit-bridge.yaml",
  "phase_status": "done",
  "weight": 25,
  "snapshotted_at": "2026-06-15T02:52:00.461Z",
  "source_sha256": "016ed19f12e33ce2675b2ca4c408583fcebcfb06d639ed12ab9d1c026fd7066e",
  "path_sha256": "730197a515b2b850077dd86b441e29ff42d8d4d7e033ee5e84eb0746c1668bfb",
  "tasks": [
    {
      "id": "P18-T1",
      "status": "done",
      "terminal_evidence": {
        "kind": "progress_events",
        "event_ids": [
          "edc2f023b3751c9d5342eddf44ae309a5042498a75354fc8d94f9b3e2fb762ce"
        ]
      }
    },
    {
      "id": "P18-T2",
      "status": "done",
      "depends_on": [
        "P18-T1"
      ],
      "terminal_evidence": {
        "kind": "progress_events",
        "event_ids": [
          "9a8758f9d424e29b4cd48ffefd84567ac156c06017a362eb7f51c949d6b22f74"
        ]
      }
    },
    {
      "id": "P18-T3",
      "status": "done",
      "depends_on": [
        "P18-T2"
      ],
      "terminal_evidence": {
        "kind": "progress_events",
        "event_ids": [
          "d6f312357f7385bf22aa0a886cb924a1f130ff944a4d39e5f5c47c7bd66f7eef"
        ]
      }
    },
    {
      "id": "P18-T4",
      "status": "done",
      "depends_on": [
        "P18-T2"
      ],
      "terminal_evidence": {
        "kind": "progress_events",
        "event_ids": [
          "76a3ddc0d8672121e6a1a8fecd86aaf20467c2a32f08a31a0b3338beda9bd2b1"
        ]
      }
    },
    {
      "id": "P18-T5",
      "status": "done",
      "depends_on": [
        "P18-T1",
        "P18-T2",
        "P18-T3",
        "P18-T4"
      ],
      "terminal_evidence": {
        "kind": "progress_events",
        "event_ids": [
          "aa95284ce3f1d7d5684b984ab30603b3448477209adc3d46a6910c5b94255b30"
        ]
      }
    }
  ]
}
